vexdb/__init__.py
vexdb/__main__.py
vexdb/vexdb.py
vexdb-1.0.15.dist-info/LICENSE
vexdb-1.0.15.dist-info/METADATA
vexdb-1.0.15.dist-info/WHEEL
vexdb-1.0.15.dist-info/top_level.txt
vexdb-1.0.15.dist-info/RECORD
