Metadata-Version: 2.1
Name: vexdb
Version: 1.0.15
Summary: A thin python wrapper for the vexDB API
Home-page: https://github.com/dhmmjoph/python-vexdb
Author: John Holbrook
Author-email: contact@johnholbrook.us
License: UNKNOWN
Platform: UNKNOWN
Classifier: Programming Language :: Python :: 3
Classifier: License :: OSI Approved :: MIT License
Classifier: Operating System :: OS Independent
